Metadata-Version: 1.0
Name: lphello
Version: 0.0.9
Summary: hello world
Home-page: https://github.com/gxfca/gitTest
Author: gxf
Author-email: feng.gao@laipac.com
License: UNKNOWN
Platform: UNKNOWN
